mapyde/__init__.py
mapyde/_version.py
mapyde/_version.pyi
mapyde/container.py
mapyde/prefix.py
mapyde/py.typed
mapyde/runner.py
mapyde/typing.py
mapyde/utils.py
mapyde/backends/__init__.py
mapyde/backends/madgraph.py
mapyde/cli/__init__.py
mapyde/cli/config.py
mapyde/cli/run.py
mapyde-0.5.0.data/data/share/mapyde/cards/delphes/FCChh.tcl
mapyde-0.5.0.data/data/share/mapyde/cards/delphes/FCChh_PileUp.tcl
mapyde-0.5.0.data/data/share/mapyde/cards/delphes/delphes_card_ATLAS.tcl
mapyde-0.5.0.data/data/share/mapyde/cards/delphes/delphes_card_ATLAS_fixedbtageffic.tcl
mapyde-0.5.0.data/data/share/mapyde/cards/delphes/delphes_card_ATLAS_lowptleptons.tcl
mapyde-0.5.0.data/data/share/mapyde/cards/delphes/delphes_card_ATLAS_lowptleptons_sleptons.tcl
mapyde-0.5.0.data/data/share/mapyde/cards/delphes/delphes_card_ATLAS_lowptleptons_sleptons_notrackineffic.tcl
mapyde-0.5.0.data/data/share/mapyde/cards/delphes/dzResolutionVsP.tcl
mapyde-0.5.0.data/data/share/mapyde/cards/delphes/momentumResolutionVsP.tcl
mapyde-0.5.0.data/data/share/mapyde/cards/delphes/muonMomentumResolutionVsP.tcl
mapyde-0.5.0.data/data/share/mapyde/cards/madspin/isr2L_c1c1_nodecays
mapyde-0.5.0.data/data/share/mapyde/cards/madspin/isr2L_n2c1_nodecays
mapyde-0.5.0.data/data/share/mapyde/cards/madspin/isr2L_n2c1_nojets_nodecays
mapyde-0.5.0.data/data/share/mapyde/cards/madspin/isr2L_n2c1m_nodecays
mapyde-0.5.0.data/data/share/mapyde/cards/madspin/isr2L_n2c1m_nojets_nodecays
mapyde-0.5.0.data/data/share/mapyde/cards/madspin/isr2L_n2c1p_nodecays
mapyde-0.5.0.data/data/share/mapyde/cards/madspin/isr2L_n2c1p_nojets_nodecays
mapyde-0.5.0.data/data/share/mapyde/cards/madspin/isr2L_n2n1_nodecays
mapyde-0.5.0.data/data/share/mapyde/cards/madspin/isr2L_n2n1_nojets_nodecays
mapyde-0.5.0.data/data/share/mapyde/cards/param/GluinoBino.slha
mapyde-0.5.0.data/data/share/mapyde/cards/param/Higgsino.slha
mapyde-0.5.0.data/data/share/mapyde/cards/param/Higgsino_CMS_v4.slha
mapyde-0.5.0.dist-info/METADATA
mapyde-0.5.0.dist-info/WHEEL
mapyde-0.5.0.dist-info/entry_points.txt
mapyde-0.5.0.dist-info/licenses/LICENSE
mapyde-0.5.0.dist-info/RECORD
