Metadata-Version: 2.1
Name: mapyde
Version: 0.5.0
Summary: Generation, simulation, analysis, and statistical inference in one go.
Project-URL: Homepage, https://scipp-atlas.github.io/mapyde/latest/
Project-URL: Documentation, https://scipp-atlas.github.io/mapyde/0.5/
Project-URL: Tracker, https://github.com/scipp-atlas/mapyde/issues
Project-URL: Source, https://github.com/scipp-atlas/mapyde
Author-email: Giordon Stark <kratsg@gmail.com>
Maintainer-email: Mike Hance <mhance@ucsc.edu>
License-File: LICENSE
Classifier: Development Status :: 1 - Planning
Classifier: Intended Audience :: Developers
Classifier: Intended Audience :: Science/Research
Classifier: License :: OSI Approved :: Apache Software License
Classifier: License :: OSI Approved :: BSD License
Classifier: Operating System :: OS Independent
Classifier: Programming Language :: Python
Classifier: Programming Language :: Python :: 3
Classifier: Programming Language :: Python :: 3.7
Classifier: Programming Language :: Python :: 3.8
Classifier: Programming Language :: Python :: 3.9
Classifier: Programming Language :: Python :: 3.10
Classifier: Topic :: Scientific/Engineering
Requires-Python: >=3.7
Requires-Dist: importlib-resources>=1.3.0; python_version < '3.9'
Requires-Dist: in-place
Requires-Dist: jinja2
Requires-Dist: tomli-w
Requires-Dist: tomli; python_version < '3.11'
Requires-Dist: trogon
Requires-Dist: typer
Requires-Dist: typing-extensions>=3.7; python_version < '3.11'
